stanfordcorenlp/__init__.py
stanfordcorenlp/corenlp.py
stanfordcorenlp-3.8.0.1.dist-info/DESCRIPTION.rst
stanfordcorenlp-3.8.0.1.dist-info/METADATA
stanfordcorenlp-3.8.0.1.dist-info/RECORD
stanfordcorenlp-3.8.0.1.dist-info/WHEEL
stanfordcorenlp-3.8.0.1.dist-info/metadata.json
stanfordcorenlp-3.8.0.1.dist-info/top_level.txt
